{
  "source": {
    "imagePath": "scatter-crosslink-modulus.png",
    "note": "Synthetic ground truth \u2014 the exact values the figure was rendered from. For a self-test / accuracy score."
  },
  "graphType": "xy",
  "axes": {
    "x": {
      "label": "Crosslinker concentration (mol%)",
      "min": 0,
      "max": 10
    },
    "y": {
      "label": "Compressive modulus (kPa)",
      "min": 0,
      "max": 120
    }
  },
  "series": [
    {
      "name": "modulus",
      "points": [
        {
          "x": 0.5474,
          "y": 26.582
        },
        {
          "x": 0.8211,
          "y": 18.492
        },
        {
          "x": 1.8518,
          "y": 34.372
        },
        {
          "x": 1.8571,
          "y": 21.332
        },
        {
          "x": 1.8901,
          "y": 29.175
        },
        {
          "x": 2.2316,
          "y": 27.539
        },
        {
          "x": 2.4378,
          "y": 33.513
        },
        {
          "x": 2.7938,
          "y": 32.028
        },
        {
          "x": 3.2015,
          "y": 35.473
        },
        {
          "x": 3.2273,
          "y": 45.157
        },
        {
          "x": 3.9887,
          "y": 53.929
        },
        {
          "x": 4.6959,
          "y": 52.84
        },
        {
          "x": 4.9719,
          "y": 55.888
        },
        {
          "x": 5.0409,
          "y": 64.756
        },
        {
          "x": 5.3703,
          "y": 63.853
        },
        {
          "x": 5.8099,
          "y": 62.465
        },
        {
          "x": 6.0996,
          "y": 60.92
        },
        {
          "x": 6.1259,
          "y": 72.287
        },
        {
          "x": 6.242,
          "y": 68.056
        },
        {
          "x": 7.1759,
          "y": 69.341
        },
        {
          "x": 7.4812,
          "y": 76.837
        },
        {
          "x": 7.6736,
          "y": 80.556
        },
        {
          "x": 8.1244,
          "y": 89.714
        },
        {
          "x": 8.3421,
          "y": 105.252
        },
        {
          "x": 8.423,
          "y": 92.465
        },
        {
          "x": 9.4595,
          "y": 98.662
        }
      ]
    }
  ]
}